<?xml version="1.0" encoding="UTF-8"?>
<typeSystemDescription xmlns="http://uima.apache.org/resourceSpecifier">
  <name>RoleTypeDescriptor</name>
  <description/>
  <version>1.0</version>
  <vendor>Alejandro Rago</vendor>
  <imports>
    <import location="../IdentifiableTypeDescriptor.xml"/>
  </imports>
  <types>
    <typeDescription>
      <name>edu.isistan.uima.unified.typesystems.srl.Role</name>
      <description/>
      <supertypeName>edu.isistan.uima.unified.typesystems.IdentifiableAnnotation</supertypeName>
      <features>
        <featureDescription>
          <name>kind</name>
          <description/>
          <rangeTypeName>uima.cas.String</rangeTypeName>
        </featureDescription>
        <featureDescription>
          <name>descriptions</name>
          <description/>
          <rangeTypeName>uima.cas.StringArray</rangeTypeName>
        </featureDescription>
        <featureDescription>
          <name>ocurrencies</name>
          <description/>
          <rangeTypeName>uima.cas.FSArray</rangeTypeName>
          <elementType>uima.cas.FSArray</elementType>
        </featureDescription>
      </features>
    </typeDescription>
  </types>
</typeSystemDescription>
